{
  "page_key": "overview",
  "page_label": "오버뷰",
  "generated_at": "2026-04-17T00:00:52+00:00",
  "market": "binance-usdt-perpetual",
  "data_source": "batch_fallback",
  "universe_key": "top100",
  "universe_label": "Top 100 Symbols",
  "timeframe": "1h",
  "timeframe_label": "1h",
  "summary_cards": [
    {
      "label": "총 미결제약정",
      "value": 9075000000.0,
      "format": "currency",
      "note": "상위 10개 심볼 합산"
    },
    {
      "label": "24h 청산 압력",
      "value": 767955.97,
      "format": "currency",
      "note": "변동성 기반 추정치"
    },
    {
      "label": "평균 펀딩비",
      "value": -0.001,
      "format": "percent",
      "note": "선택 타임프레임 기준"
    },
    {
      "label": "평균 롱/숏 비율",
      "value": 0.968,
      "format": "ratio",
      "note": "계정 비율 평균"
    }
  ],
  "status_counts": [
    {
      "key": "forming",
      "label": "forming",
      "count": 0
    },
    {
      "key": "touch",
      "label": "touch",
      "count": 1
    },
    {
      "key": "tbar_complete",
      "label": "tbar_complete",
      "count": 1
    },
    {
      "key": "complete",
      "label": "complete",
      "count": 0
    }
  ],
  "top_opportunities": [
    {
      "symbol": "SOLUSDT",
      "timeframe": "1h",
      "timeframe_label": "1h",
      "last_price": 80.06,
      "change_24h": 3.6,
      "quote_volume": 1280000000.0,
      "funding_rate": -0.0048,
      "open_interest_usd": 987000000.0,
      "long_short_ratio": 1.01,
      "liquidation_pressure_usd": 97874.51,
      "scores": {
        "moving_average": 54.0,
        "oscillator": -31.9,
        "technical": 25.2,
        "trend": 61.9,
        "trend_bias": 47.1,
        "momentum": 23.4,
        "momentum_bias": -23.4,
        "volatility": 90.2,
        "derivatives": 14.4,
        "derivatives_bias": 9.9,
        "opportunity": 70.0,
        "setup_bias": 23.1
      },
      "labels": {
        "technical_rating": "Buy",
        "trend_bias": "상승 추세",
        "momentum_bias": "과매도",
        "volatility_state": "압축",
        "derivatives_bias": "중립",
        "setup_bias": "롱 우위"
      },
      "side": "long",
      "side_label": "롱",
      "signals": {
        "squeeze": true,
        "breakout_up": false,
        "breakout_down": false,
        "divergence_candidate": false,
        "supertrend": "bullish",
        "ichimoku_bias": "neutral"
      },
      "indicators": {
        "ema20": 80.111,
        "ema50": 79.825,
        "ema200": 78.757,
        "rsi14": 51.94,
        "stoch_rsi": 0.0,
        "macd_line": 0.14237,
        "macd_signal": 0.15836,
        "macd_histogram": -0.01599,
        "bollinger_lower": 79.835,
        "bollinger_mid": 80.122,
        "bollinger_upper": 80.409,
        "bb_width": 0.72,
        "atr14": 0.41914,
        "atr_pct": 0.52,
        "adx14": 97.52,
        "plus_di": 8.01,
        "minus_di": 1.65,
        "supertrend_value": 79.035,
        "vwap": 78.598,
        "close_vs_vwap_pct": 1.86,
        "roc12": -0.03,
        "ichimoku": {
          "tenkan": 80.262,
          "kijun": 80.008,
          "span_a": 80.135,
          "span_b": 79.845,
          "bias": "neutral"
        }
      },
      "pattern": {
        "pattern": "Gartley",
        "status": "touch",
        "status_label": "Realtime Touch",
        "score": 75.6,
        "score_breakdown": {
          "ratio_fit": 31.4,
          "geometry": 18.3,
          "reaction": 12.0,
          "indicators": 14.5
        },
        "summary": "Gartley 패턴이 PRZ 구간에 진입했고 실시간 터치 상태로 분류되었습니다.",
        "preview_image": "generated/scanner/scan-top100-1h/solusdt-gartley-touch.svg",
        "detail_page": "crypto/setups/scan-top100-1h/solusdt-gartley-touch/",
        "legacy_detail_page": "patterns/1h/solusdt-gartley-touch/",
        "detail_data_path": "setups/scan-top100-1h/solusdt-gartley-touch.json",
        "side": "bullish",
        "side_label": "Bullish (매수)",
        "prz": {
          "lower": 79.9831,
          "upper": 80.0527,
          "center": 80.018,
          "distance_pct": 0.052
        },
        "targets": {
          "tp1": 80.2336,
          "tp2": 80.3714
        },
        "stop": {
          "value": 79.1411,
          "label": "1.13 XA"
        },
        "points": {
          "X": {
            "price": 79.92,
            "timestamp": "2026-04-04T07:45:00+00:00",
            "index": 24
          },
          "A": {
            "price": 80.54,
            "timestamp": "2026-04-04T08:30:00+00:00",
            "index": 38
          },
          "B": {
            "price": 80.15,
            "timestamp": "2026-04-04T08:55:00+00:00",
            "index": 49
          },
          "C": {
            "price": 80.42,
            "timestamp": "2026-04-04T09:30:00+00:00",
            "index": 63
          },
          "D": {
            "price": 80.06,
            "timestamp": "2026-04-04T10:30:00+00:00",
            "index": 79
          }
        },
        "ratios": {
          "xab": 0.629,
          "abc": 0.692,
          "bcd": 1.333,
          "xad": 0.774
        },
        "indicator_flags": [
          {
            "key": "rsi",
            "label": "RSI",
            "status": "pass",
            "value": "41.5",
            "note": "과매도/과매수 구간 접근"
          },
          {
            "key": "macd",
            "label": "MACD",
            "status": "pass",
            "value": "0.0038",
            "note": "히스토그램 반전 확인"
          },
          {
            "key": "bollinger",
            "label": "Bollinger",
            "status": "pass",
            "value": "79.98 ~ 80.62",
            "note": "밴드 극단값 근접"
          },
          {
            "key": "vwap",
            "label": "VWAP",
            "status": "pass",
            "value": "80.17",
            "note": "VWAP 회복/이탈 흐름"
          }
        ]
      },
      "flags": [
        "볼린저 압축"
      ],
      "data_origin": "fallback_synthetic",
      "normalized_quote_volume": 0.0,
      "normalized_open_interest_usd": 0.0,
      "universe_score": 0.0
    },
    {
      "symbol": "AVAXUSDT",
      "timeframe": "1h",
      "timeframe_label": "1h",
      "last_price": 38.14,
      "change_24h": -5.4,
      "quote_volume": 254000000.0,
      "funding_rate": -0.0096,
      "open_interest_usd": 164000000.0,
      "long_short_ratio": 0.85,
      "liquidation_pressure_usd": 27775.64,
      "scores": {
        "moving_average": -100,
        "oscillator": -57.7,
        "technical": -82.6,
        "trend": 90.7,
        "trend_bias": -87.1,
        "momentum": 57.8,
        "momentum_bias": -57.8,
        "volatility": 90.2,
        "derivatives": 12.3,
        "derivatives_bias": 30.9,
        "opportunity": 69.9,
        "setup_bias": -79.2
      },
      "labels": {
        "technical_rating": "Strong Sell",
        "trend_bias": "하락 추세",
        "momentum_bias": "과매도",
        "volatility_state": "압축",
        "derivatives_bias": "숏 과밀",
        "setup_bias": "숏 우위"
      },
      "side": "short",
      "side_label": "숏",
      "signals": {
        "squeeze": true,
        "breakout_up": false,
        "breakout_down": true,
        "divergence_candidate": false,
        "supertrend": "bearish",
        "ichimoku_bias": "bearish"
      },
      "indicators": {
        "ema20": 38.417,
        "ema50": 38.507,
        "ema200": 39.155,
        "rsi14": 0.0,
        "stoch_rsi": 0.0,
        "macd_line": -0.05335,
        "macd_signal": -0.03594,
        "macd_histogram": -0.01741,
        "bollinger_lower": 38.287,
        "bollinger_mid": 38.431,
        "bollinger_upper": 38.574,
        "bb_width": 0.74,
        "atr14": 0.19748,
        "atr_pct": 0.52,
        "adx14": 99.84,
        "plus_di": 0.0,
        "minus_di": 11.36,
        "supertrend_value": 38.96,
        "vwap": 39.242,
        "close_vs_vwap_pct": -2.81,
        "roc12": -0.83,
        "ichimoku": {
          "tenkan": 38.351,
          "kijun": 38.384,
          "span_a": 38.368,
          "span_b": 38.469,
          "bias": "bearish"
        }
      },
      "pattern": null,
      "flags": [
        "기술 Strong Sell",
        "볼린저 압축",
        "하방 돌파"
      ],
      "data_origin": "fallback_synthetic",
      "normalized_quote_volume": 0.0,
      "normalized_open_interest_usd": 0.0,
      "universe_score": 0.0
    },
    {
      "symbol": "XRPUSDT",
      "timeframe": "1h",
      "timeframe_label": "1h",
      "last_price": 0.642,
      "change_24h": -4.5,
      "quote_volume": 1140000000.0,
      "funding_rate": -0.0024,
      "open_interest_usd": 602000000.0,
      "long_short_ratio": 0.905,
      "liquidation_pressure_usd": 80900.59,
      "scores": {
        "moving_average": -100,
        "oscillator": -57.4,
        "technical": -81.3,
        "trend": 89.6,
        "trend_bias": -85.6,
        "momentum": 56.2,
        "momentum_bias": -56.2,
        "volatility": 90.4,
        "derivatives": 12.1,
        "derivatives_bias": 11.5,
        "opportunity": 69.1,
        "setup_bias": -77.8
      },
      "labels": {
        "technical_rating": "Strong Sell",
        "trend_bias": "하락 추세",
        "momentum_bias": "과매도",
        "volatility_state": "압축",
        "derivatives_bias": "중립",
        "setup_bias": "숏 우위"
      },
      "side": "short",
      "side_label": "숏",
      "signals": {
        "squeeze": true,
        "breakout_up": false,
        "breakout_down": true,
        "divergence_candidate": false,
        "supertrend": "bearish",
        "ichimoku_bias": "bearish"
      },
      "indicators": {
        "ema20": 0.64571,
        "ema50": 0.64749,
        "ema200": 0.65568,
        "rsi14": 0.06,
        "stoch_rsi": 0.0,
        "macd_line": -0.00117,
        "macd_signal": -0.00093,
        "macd_histogram": -0.00024,
        "bollinger_lower": 0.64343,
        "bollinger_mid": 0.64594,
        "bollinger_upper": 0.64845,
        "bb_width": 0.78,
        "atr14": 0.003653,
        "atr_pct": 0.57,
        "adx14": 98.85,
        "plus_di": 0.02,
        "minus_di": 7.93,
        "supertrend_value": 0.65413,
        "vwap": 0.65683,
        "close_vs_vwap_pct": -2.26,
        "roc12": -0.7,
        "ichimoku": {
          "tenkan": 0.64463,
          "kijun": 0.6459,
          "span_a": 0.64527,
          "span_b": 0.64736,
          "bias": "bearish"
        }
      },
      "pattern": null,
      "flags": [
        "기술 Strong Sell",
        "볼린저 압축",
        "하방 돌파"
      ],
      "data_origin": "fallback_synthetic",
      "normalized_quote_volume": 0.0,
      "normalized_open_interest_usd": 0.0,
      "universe_score": 0.0
    },
    {
      "symbol": "ETHUSDT",
      "timeframe": "1h",
      "timeframe_label": "1h",
      "last_price": 3315.0,
      "change_24h": -2.7,
      "quote_volume": 4280000000.0,
      "funding_rate": -0.0072,
      "open_interest_usd": 1920000000.0,
      "long_short_ratio": 0.955,
      "liquidation_pressure_usd": 147744.0,
      "scores": {
        "moving_average": -100,
        "oscillator": -56.5,
        "technical": -78.9,
        "trend": 77.5,
        "trend_bias": -83.0,
        "momentum": 52.9,
        "momentum_bias": -52.9,
        "volatility": 90.0,
        "derivatives": 28.1,
        "derivatives_bias": 18.8,
        "opportunity": 68.3,
        "setup_bias": -75.1
      },
      "labels": {
        "technical_rating": "Strong Sell",
        "trend_bias": "하락 추세",
        "momentum_bias": "과매도",
        "volatility_state": "압축",
        "derivatives_bias": "중립",
        "setup_bias": "숏 우위"
      },
      "side": "short",
      "side_label": "숏",
      "signals": {
        "squeeze": true,
        "breakout_up": false,
        "breakout_down": true,
        "divergence_candidate": false,
        "supertrend": "bearish",
        "ichimoku_bias": "bearish"
      },
      "indicators": {
        "ema20": 3321.16,
        "ema50": 3321.87,
        "ema200": 3354.39,
        "rsi14": 14.88,
        "stoch_rsi": 0.0,
        "macd_line": -0.48506,
        "macd_signal": 0.45741,
        "macd_histogram": -0.94247,
        "bollinger_lower": 3318.14,
        "bollinger_mid": 3322.47,
        "bollinger_upper": 3326.79,
        "bb_width": 0.26,
        "atr14": 16.01,
        "atr_pct": 0.48,
        "adx14": 31.76,
        "plus_di": 1.91,
        "minus_di": 4.19,
        "supertrend_value": 3363.72,
        "vwap": 3357.96,
        "close_vs_vwap_pct": -1.28,
        "roc12": -0.27,
        "ichimoku": {
          "tenkan": 3322.09,
          "kijun": 3322.98,
          "span_a": 3322.54,
          "span_b": 3318.18,
          "bias": "bearish"
        }
      },
      "pattern": null,
      "flags": [
        "기술 Strong Sell",
        "볼린저 압축",
        "하방 돌파"
      ],
      "data_origin": "fallback_synthetic",
      "normalized_quote_volume": 0.0,
      "normalized_open_interest_usd": 0.0,
      "universe_score": 0.0
    },
    {
      "symbol": "LINKUSDT",
      "timeframe": "1h",
      "timeframe_label": "1h",
      "last_price": 18.28,
      "change_24h": 4.5,
      "quote_volume": 281000000.0,
      "funding_rate": 0.0096,
      "open_interest_usd": 176000000.0,
      "long_short_ratio": 0.955,
      "liquidation_pressure_usd": 22572.0,
      "scores": {
        "moving_average": 100,
        "oscillator": 56.4,
        "technical": 80.8,
        "trend": 89.1,
        "trend_bias": 84.8,
        "momentum": 55.1,
        "momentum_bias": 55.1,
        "volatility": 90.1,
        "derivatives": 8.2,
        "derivatives_bias": -18.2,
        "opportunity": 67.9,
        "setup_bias": 77.1
      },
      "labels": {
        "technical_rating": "Strong Buy",
        "trend_bias": "상승 추세",
        "momentum_bias": "과매수",
        "volatility_state": "압축",
        "derivatives_bias": "중립",
        "setup_bias": "롱 우위"
      },
      "side": "long",
      "side_label": "롱",
      "signals": {
        "squeeze": true,
        "breakout_up": false,
        "breakout_down": false,
        "divergence_candidate": false,
        "supertrend": "bullish",
        "ichimoku_bias": "bullish"
      },
      "indicators": {
        "ema20": 18.245,
        "ema50": 18.205,
        "ema200": 17.929,
        "rsi14": 98.75,
        "stoch_rsi": 100.0,
        "macd_line": 0.02271,
        "macd_signal": 0.02242,
        "macd_histogram": 0.00029,
        "bollinger_lower": 18.207,
        "bollinger_mid": 18.246,
        "bollinger_upper": 18.285,
        "bb_width": 0.43,
        "atr14": 0.093558,
        "atr_pct": 0.51,
        "adx14": 91.58,
        "plus_di": 6.5,
        "minus_di": 0.18,
        "supertrend_value": 17.992,
        "vwap": 17.892,
        "close_vs_vwap_pct": 2.17,
        "roc12": 0.22,
        "ichimoku": {
          "tenkan": 18.265,
          "kijun": 18.231,
          "span_a": 18.248,
          "span_b": 18.203,
          "bias": "bullish"
        }
      },
      "pattern": null,
      "flags": [
        "기술 Strong Buy",
        "볼린저 압축"
      ],
      "data_origin": "fallback_synthetic",
      "normalized_quote_volume": 0.0,
      "normalized_open_interest_usd": 0.0,
      "universe_score": 0.0
    },
    {
      "symbol": "SUIUSDT",
      "timeframe": "1h",
      "timeframe_label": "1h",
      "last_price": 1.64,
      "change_24h": -3.6,
      "quote_volume": 326000000.0,
      "funding_rate": 0.0072,
      "open_interest_usd": 145000000.0,
      "long_short_ratio": 0.9,
      "liquidation_pressure_usd": 15660.0,
      "scores": {
        "moving_average": -100,
        "oscillator": -56.4,
        "technical": -80.0,
        "trend": 75.6,
        "trend_bias": -83.5,
        "momentum": 54.1,
        "momentum_bias": -54.1,
        "volatility": 90.1,
        "derivatives": 9.0,
        "derivatives_bias": -9.3,
        "opportunity": 65.0,
        "setup_bias": -76.0
      },
      "labels": {
        "technical_rating": "Strong Sell",
        "trend_bias": "하락 추세",
        "momentum_bias": "과매도",
        "volatility_state": "압축",
        "derivatives_bias": "중립",
        "setup_bias": "숏 우위"
      },
      "side": "short",
      "side_label": "숏",
      "signals": {
        "squeeze": true,
        "breakout_up": false,
        "breakout_down": true,
        "divergence_candidate": false,
        "supertrend": "bearish",
        "ichimoku_bias": "bearish"
      },
      "indicators": {
        "ema20": 1.6421,
        "ema50": 1.6442,
        "ema200": 1.6671,
        "rsi14": 8.67,
        "stoch_rsi": 0.0,
        "macd_line": -0.00058,
        "macd_signal": -0.00037,
        "macd_histogram": -0.00021,
        "bollinger_lower": 1.6407,
        "bollinger_mid": 1.6424,
        "bollinger_upper": 1.6441,
        "bb_width": 0.21,
        "atr14": 0.008177,
        "atr_pct": 0.5,
        "adx14": 27.7,
        "plus_di": 1.31,
        "minus_di": 4.54,
        "supertrend_value": 1.6666,
        "vwap": 1.6699,
        "close_vs_vwap_pct": -1.79,
        "roc12": -0.19,
        "ichimoku": {
          "tenkan": 1.6422,
          "kijun": 1.6425,
          "span_a": 1.6423,
          "span_b": 1.6429,
          "bias": "bearish"
        }
      },
      "pattern": null,
      "flags": [
        "기술 Strong Sell",
        "볼린저 압축",
        "하방 돌파"
      ],
      "data_origin": "fallback_synthetic",
      "normalized_quote_volume": 0.0,
      "normalized_open_interest_usd": 0.0,
      "universe_score": 0.0
    }
  ],
  "top_patterns": [
    {
      "symbol": "SOLUSDT",
      "timeframe": "1h",
      "timeframe_label": "1h",
      "last_price": 80.06,
      "change_24h": 3.6,
      "quote_volume": 1280000000.0,
      "funding_rate": -0.0048,
      "open_interest_usd": 987000000.0,
      "long_short_ratio": 1.01,
      "liquidation_pressure_usd": 97874.51,
      "scores": {
        "moving_average": 54.0,
        "oscillator": -31.9,
        "technical": 25.2,
        "trend": 61.9,
        "trend_bias": 47.1,
        "momentum": 23.4,
        "momentum_bias": -23.4,
        "volatility": 90.2,
        "derivatives": 14.4,
        "derivatives_bias": 9.9,
        "opportunity": 70.0,
        "setup_bias": 23.1
      },
      "labels": {
        "technical_rating": "Buy",
        "trend_bias": "상승 추세",
        "momentum_bias": "과매도",
        "volatility_state": "압축",
        "derivatives_bias": "중립",
        "setup_bias": "롱 우위"
      },
      "side": "long",
      "side_label": "롱",
      "signals": {
        "squeeze": true,
        "breakout_up": false,
        "breakout_down": false,
        "divergence_candidate": false,
        "supertrend": "bullish",
        "ichimoku_bias": "neutral"
      },
      "indicators": {
        "ema20": 80.111,
        "ema50": 79.825,
        "ema200": 78.757,
        "rsi14": 51.94,
        "stoch_rsi": 0.0,
        "macd_line": 0.14237,
        "macd_signal": 0.15836,
        "macd_histogram": -0.01599,
        "bollinger_lower": 79.835,
        "bollinger_mid": 80.122,
        "bollinger_upper": 80.409,
        "bb_width": 0.72,
        "atr14": 0.41914,
        "atr_pct": 0.52,
        "adx14": 97.52,
        "plus_di": 8.01,
        "minus_di": 1.65,
        "supertrend_value": 79.035,
        "vwap": 78.598,
        "close_vs_vwap_pct": 1.86,
        "roc12": -0.03,
        "ichimoku": {
          "tenkan": 80.262,
          "kijun": 80.008,
          "span_a": 80.135,
          "span_b": 79.845,
          "bias": "neutral"
        }
      },
      "pattern": {
        "pattern": "Gartley",
        "status": "touch",
        "status_label": "Realtime Touch",
        "score": 75.6,
        "score_breakdown": {
          "ratio_fit": 31.4,
          "geometry": 18.3,
          "reaction": 12.0,
          "indicators": 14.5
        },
        "summary": "Gartley 패턴이 PRZ 구간에 진입했고 실시간 터치 상태로 분류되었습니다.",
        "preview_image": "generated/scanner/scan-top100-1h/solusdt-gartley-touch.svg",
        "detail_page": "crypto/setups/scan-top100-1h/solusdt-gartley-touch/",
        "legacy_detail_page": "patterns/1h/solusdt-gartley-touch/",
        "detail_data_path": "setups/scan-top100-1h/solusdt-gartley-touch.json",
        "side": "bullish",
        "side_label": "Bullish (매수)",
        "prz": {
          "lower": 79.9831,
          "upper": 80.0527,
          "center": 80.018,
          "distance_pct": 0.052
        },
        "targets": {
          "tp1": 80.2336,
          "tp2": 80.3714
        },
        "stop": {
          "value": 79.1411,
          "label": "1.13 XA"
        },
        "points": {
          "X": {
            "price": 79.92,
            "timestamp": "2026-04-04T07:45:00+00:00",
            "index": 24
          },
          "A": {
            "price": 80.54,
            "timestamp": "2026-04-04T08:30:00+00:00",
            "index": 38
          },
          "B": {
            "price": 80.15,
            "timestamp": "2026-04-04T08:55:00+00:00",
            "index": 49
          },
          "C": {
            "price": 80.42,
            "timestamp": "2026-04-04T09:30:00+00:00",
            "index": 63
          },
          "D": {
            "price": 80.06,
            "timestamp": "2026-04-04T10:30:00+00:00",
            "index": 79
          }
        },
        "ratios": {
          "xab": 0.629,
          "abc": 0.692,
          "bcd": 1.333,
          "xad": 0.774
        },
        "indicator_flags": [
          {
            "key": "rsi",
            "label": "RSI",
            "status": "pass",
            "value": "41.5",
            "note": "과매도/과매수 구간 접근"
          },
          {
            "key": "macd",
            "label": "MACD",
            "status": "pass",
            "value": "0.0038",
            "note": "히스토그램 반전 확인"
          },
          {
            "key": "bollinger",
            "label": "Bollinger",
            "status": "pass",
            "value": "79.98 ~ 80.62",
            "note": "밴드 극단값 근접"
          },
          {
            "key": "vwap",
            "label": "VWAP",
            "status": "pass",
            "value": "80.17",
            "note": "VWAP 회복/이탈 흐름"
          }
        ]
      },
      "flags": [
        "볼린저 압축"
      ],
      "data_origin": "fallback_synthetic",
      "normalized_quote_volume": 0.0,
      "normalized_open_interest_usd": 0.0,
      "universe_score": 0.0
    }
  ],
  "top_signals": [
    {
      "symbol": "ETHUSDT",
      "timeframe": "1h",
      "timeframe_label": "1h",
      "last_price": 3315.0,
      "change_24h": -2.7,
      "quote_volume": 4280000000.0,
      "funding_rate": -0.0072,
      "open_interest_usd": 1920000000.0,
      "long_short_ratio": 0.955,
      "liquidation_pressure_usd": 147744.0,
      "scores": {
        "moving_average": -100,
        "oscillator": -56.5,
        "technical": -78.9,
        "trend": 77.5,
        "trend_bias": -83.0,
        "momentum": 52.9,
        "momentum_bias": -52.9,
        "volatility": 90.0,
        "derivatives": 28.1,
        "derivatives_bias": 18.8,
        "opportunity": 68.3,
        "setup_bias": -75.1
      },
      "labels": {
        "technical_rating": "Strong Sell",
        "trend_bias": "하락 추세",
        "momentum_bias": "과매도",
        "volatility_state": "압축",
        "derivatives_bias": "중립",
        "setup_bias": "숏 우위"
      },
      "side": "short",
      "side_label": "숏",
      "signals": {
        "squeeze": true,
        "breakout_up": false,
        "breakout_down": true,
        "divergence_candidate": false,
        "supertrend": "bearish",
        "ichimoku_bias": "bearish"
      },
      "indicators": {
        "ema20": 3321.16,
        "ema50": 3321.87,
        "ema200": 3354.39,
        "rsi14": 14.88,
        "stoch_rsi": 0.0,
        "macd_line": -0.48506,
        "macd_signal": 0.45741,
        "macd_histogram": -0.94247,
        "bollinger_lower": 3318.14,
        "bollinger_mid": 3322.47,
        "bollinger_upper": 3326.79,
        "bb_width": 0.26,
        "atr14": 16.01,
        "atr_pct": 0.48,
        "adx14": 31.76,
        "plus_di": 1.91,
        "minus_di": 4.19,
        "supertrend_value": 3363.72,
        "vwap": 3357.96,
        "close_vs_vwap_pct": -1.28,
        "roc12": -0.27,
        "ichimoku": {
          "tenkan": 3322.09,
          "kijun": 3322.98,
          "span_a": 3322.54,
          "span_b": 3318.18,
          "bias": "bearish"
        }
      },
      "pattern": null,
      "flags": [
        "기술 Strong Sell",
        "볼린저 압축",
        "하방 돌파"
      ],
      "data_origin": "fallback_synthetic",
      "normalized_quote_volume": 0.0,
      "normalized_open_interest_usd": 0.0,
      "universe_score": 0.0
    },
    {
      "symbol": "AVAXUSDT",
      "timeframe": "1h",
      "timeframe_label": "1h",
      "last_price": 38.14,
      "change_24h": -5.4,
      "quote_volume": 254000000.0,
      "funding_rate": -0.0096,
      "open_interest_usd": 164000000.0,
      "long_short_ratio": 0.85,
      "liquidation_pressure_usd": 27775.64,
      "scores": {
        "moving_average": -100,
        "oscillator": -57.7,
        "technical": -82.6,
        "trend": 90.7,
        "trend_bias": -87.1,
        "momentum": 57.8,
        "momentum_bias": -57.8,
        "volatility": 90.2,
        "derivatives": 12.3,
        "derivatives_bias": 30.9,
        "opportunity": 69.9,
        "setup_bias": -79.2
      },
      "labels": {
        "technical_rating": "Strong Sell",
        "trend_bias": "하락 추세",
        "momentum_bias": "과매도",
        "volatility_state": "압축",
        "derivatives_bias": "숏 과밀",
        "setup_bias": "숏 우위"
      },
      "side": "short",
      "side_label": "숏",
      "signals": {
        "squeeze": true,
        "breakout_up": false,
        "breakout_down": true,
        "divergence_candidate": false,
        "supertrend": "bearish",
        "ichimoku_bias": "bearish"
      },
      "indicators": {
        "ema20": 38.417,
        "ema50": 38.507,
        "ema200": 39.155,
        "rsi14": 0.0,
        "stoch_rsi": 0.0,
        "macd_line": -0.05335,
        "macd_signal": -0.03594,
        "macd_histogram": -0.01741,
        "bollinger_lower": 38.287,
        "bollinger_mid": 38.431,
        "bollinger_upper": 38.574,
        "bb_width": 0.74,
        "atr14": 0.19748,
        "atr_pct": 0.52,
        "adx14": 99.84,
        "plus_di": 0.0,
        "minus_di": 11.36,
        "supertrend_value": 38.96,
        "vwap": 39.242,
        "close_vs_vwap_pct": -2.81,
        "roc12": -0.83,
        "ichimoku": {
          "tenkan": 38.351,
          "kijun": 38.384,
          "span_a": 38.368,
          "span_b": 38.469,
          "bias": "bearish"
        }
      },
      "pattern": null,
      "flags": [
        "기술 Strong Sell",
        "볼린저 압축",
        "하방 돌파"
      ],
      "data_origin": "fallback_synthetic",
      "normalized_quote_volume": 0.0,
      "normalized_open_interest_usd": 0.0,
      "universe_score": 0.0
    },
    {
      "symbol": "XRPUSDT",
      "timeframe": "1h",
      "timeframe_label": "1h",
      "last_price": 0.642,
      "change_24h": -4.5,
      "quote_volume": 1140000000.0,
      "funding_rate": -0.0024,
      "open_interest_usd": 602000000.0,
      "long_short_ratio": 0.905,
      "liquidation_pressure_usd": 80900.59,
      "scores": {
        "moving_average": -100,
        "oscillator": -57.4,
        "technical": -81.3,
        "trend": 89.6,
        "trend_bias": -85.6,
        "momentum": 56.2,
        "momentum_bias": -56.2,
        "volatility": 90.4,
        "derivatives": 12.1,
        "derivatives_bias": 11.5,
        "opportunity": 69.1,
        "setup_bias": -77.8
      },
      "labels": {
        "technical_rating": "Strong Sell",
        "trend_bias": "하락 추세",
        "momentum_bias": "과매도",
        "volatility_state": "압축",
        "derivatives_bias": "중립",
        "setup_bias": "숏 우위"
      },
      "side": "short",
      "side_label": "숏",
      "signals": {
        "squeeze": true,
        "breakout_up": false,
        "breakout_down": true,
        "divergence_candidate": false,
        "supertrend": "bearish",
        "ichimoku_bias": "bearish"
      },
      "indicators": {
        "ema20": 0.64571,
        "ema50": 0.64749,
        "ema200": 0.65568,
        "rsi14": 0.06,
        "stoch_rsi": 0.0,
        "macd_line": -0.00117,
        "macd_signal": -0.00093,
        "macd_histogram": -0.00024,
        "bollinger_lower": 0.64343,
        "bollinger_mid": 0.64594,
        "bollinger_upper": 0.64845,
        "bb_width": 0.78,
        "atr14": 0.003653,
        "atr_pct": 0.57,
        "adx14": 98.85,
        "plus_di": 0.02,
        "minus_di": 7.93,
        "supertrend_value": 0.65413,
        "vwap": 0.65683,
        "close_vs_vwap_pct": -2.26,
        "roc12": -0.7,
        "ichimoku": {
          "tenkan": 0.64463,
          "kijun": 0.6459,
          "span_a": 0.64527,
          "span_b": 0.64736,
          "bias": "bearish"
        }
      },
      "pattern": null,
      "flags": [
        "기술 Strong Sell",
        "볼린저 압축",
        "하방 돌파"
      ],
      "data_origin": "fallback_synthetic",
      "normalized_quote_volume": 0.0,
      "normalized_open_interest_usd": 0.0,
      "universe_score": 0.0
    },
    {
      "symbol": "LINKUSDT",
      "timeframe": "1h",
      "timeframe_label": "1h",
      "last_price": 18.28,
      "change_24h": 4.5,
      "quote_volume": 281000000.0,
      "funding_rate": 0.0096,
      "open_interest_usd": 176000000.0,
      "long_short_ratio": 0.955,
      "liquidation_pressure_usd": 22572.0,
      "scores": {
        "moving_average": 100,
        "oscillator": 56.4,
        "technical": 80.8,
        "trend": 89.1,
        "trend_bias": 84.8,
        "momentum": 55.1,
        "momentum_bias": 55.1,
        "volatility": 90.1,
        "derivatives": 8.2,
        "derivatives_bias": -18.2,
        "opportunity": 67.9,
        "setup_bias": 77.1
      },
      "labels": {
        "technical_rating": "Strong Buy",
        "trend_bias": "상승 추세",
        "momentum_bias": "과매수",
        "volatility_state": "압축",
        "derivatives_bias": "중립",
        "setup_bias": "롱 우위"
      },
      "side": "long",
      "side_label": "롱",
      "signals": {
        "squeeze": true,
        "breakout_up": false,
        "breakout_down": false,
        "divergence_candidate": false,
        "supertrend": "bullish",
        "ichimoku_bias": "bullish"
      },
      "indicators": {
        "ema20": 18.245,
        "ema50": 18.205,
        "ema200": 17.929,
        "rsi14": 98.75,
        "stoch_rsi": 100.0,
        "macd_line": 0.02271,
        "macd_signal": 0.02242,
        "macd_histogram": 0.00029,
        "bollinger_lower": 18.207,
        "bollinger_mid": 18.246,
        "bollinger_upper": 18.285,
        "bb_width": 0.43,
        "atr14": 0.093558,
        "atr_pct": 0.51,
        "adx14": 91.58,
        "plus_di": 6.5,
        "minus_di": 0.18,
        "supertrend_value": 17.992,
        "vwap": 17.892,
        "close_vs_vwap_pct": 2.17,
        "roc12": 0.22,
        "ichimoku": {
          "tenkan": 18.265,
          "kijun": 18.231,
          "span_a": 18.248,
          "span_b": 18.203,
          "bias": "bullish"
        }
      },
      "pattern": null,
      "flags": [
        "기술 Strong Buy",
        "볼린저 압축"
      ],
      "data_origin": "fallback_synthetic",
      "normalized_quote_volume": 0.0,
      "normalized_open_interest_usd": 0.0,
      "universe_score": 0.0
    },
    {
      "symbol": "SUIUSDT",
      "timeframe": "1h",
      "timeframe_label": "1h",
      "last_price": 1.64,
      "change_24h": -3.6,
      "quote_volume": 326000000.0,
      "funding_rate": 0.0072,
      "open_interest_usd": 145000000.0,
      "long_short_ratio": 0.9,
      "liquidation_pressure_usd": 15660.0,
      "scores": {
        "moving_average": -100,
        "oscillator": -56.4,
        "technical": -80.0,
        "trend": 75.6,
        "trend_bias": -83.5,
        "momentum": 54.1,
        "momentum_bias": -54.1,
        "volatility": 90.1,
        "derivatives": 9.0,
        "derivatives_bias": -9.3,
        "opportunity": 65.0,
        "setup_bias": -76.0
      },
      "labels": {
        "technical_rating": "Strong Sell",
        "trend_bias": "하락 추세",
        "momentum_bias": "과매도",
        "volatility_state": "압축",
        "derivatives_bias": "중립",
        "setup_bias": "숏 우위"
      },
      "side": "short",
      "side_label": "숏",
      "signals": {
        "squeeze": true,
        "breakout_up": false,
        "breakout_down": true,
        "divergence_candidate": false,
        "supertrend": "bearish",
        "ichimoku_bias": "bearish"
      },
      "indicators": {
        "ema20": 1.6421,
        "ema50": 1.6442,
        "ema200": 1.6671,
        "rsi14": 8.67,
        "stoch_rsi": 0.0,
        "macd_line": -0.00058,
        "macd_signal": -0.00037,
        "macd_histogram": -0.00021,
        "bollinger_lower": 1.6407,
        "bollinger_mid": 1.6424,
        "bollinger_upper": 1.6441,
        "bb_width": 0.21,
        "atr14": 0.008177,
        "atr_pct": 0.5,
        "adx14": 27.7,
        "plus_di": 1.31,
        "minus_di": 4.54,
        "supertrend_value": 1.6666,
        "vwap": 1.6699,
        "close_vs_vwap_pct": -1.79,
        "roc12": -0.19,
        "ichimoku": {
          "tenkan": 1.6422,
          "kijun": 1.6425,
          "span_a": 1.6423,
          "span_b": 1.6429,
          "bias": "bearish"
        }
      },
      "pattern": null,
      "flags": [
        "기술 Strong Sell",
        "볼린저 압축",
        "하방 돌파"
      ],
      "data_origin": "fallback_synthetic",
      "normalized_quote_volume": 0.0,
      "normalized_open_interest_usd": 0.0,
      "universe_score": 0.0
    },
    {
      "symbol": "BTCUSDT",
      "timeframe": "1h",
      "timeframe_label": "1h",
      "last_price": 68320.0,
      "change_24h": 1.8,
      "quote_volume": 9450000000.0,
      "funding_rate": -0.0096,
      "open_interest_usd": 3850000000.0,
      "long_short_ratio": 0.74,
      "liquidation_pressure_usd": 238140.0,
      "scores": {
        "moving_average": 12.0,
        "oscillator": -56.7,
        "technical": -9.2,
        "trend": 35.3,
        "trend_bias": 10.2,
        "momentum": 47.7,
        "momentum_bias": -47.7,
        "volatility": 90.1,
        "derivatives": 44.7,
        "derivatives_bias": 38.0,
        "opportunity": 35.9,
        "setup_bias": -10.1
      },
      "labels": {
        "technical_rating": "Neutral",
        "trend_bias": "혼조",
        "momentum_bias": "과매도",
        "volatility_state": "압축",
        "derivatives_bias": "숏 과밀",
        "setup_bias": "숏 우위"
      },
      "side": "short",
      "side_label": "숏",
      "signals": {
        "squeeze": true,
        "breakout_up": false,
        "breakout_down": true,
        "divergence_candidate": false,
        "supertrend": "bullish",
        "ichimoku_bias": "bearish"
      },
      "indicators": {
        "ema20": 68523.93,
        "ema50": 68427.5,
        "ema200": 67804.72,
        "rsi14": 21.3,
        "stoch_rsi": 0.0,
        "macd_line": 26.02393,
        "macd_signal": 48.29035,
        "macd_histogram": -22.26642,
        "bollinger_lower": 68417.78,
        "bollinger_mid": 68544.15,
        "bollinger_upper": 68670.53,
        "bb_width": 0.37,
        "atr14": 344.748,
        "atr_pct": 0.5,
        "adx14": 82.74,
        "plus_di": 4.29,
        "minus_di": 3.42,
        "supertrend_value": 67523.72,
        "vwap": 67721.89,
        "close_vs_vwap_pct": 0.88,
        "roc12": -0.34,
        "ichimoku": {
          "tenkan": 68574.88,
          "kijun": 68512.74,
          "span_a": 68543.81,
          "span_b": 68452.4,
          "bias": "bearish"
        }
      },
      "pattern": null,
      "flags": [
        "볼린저 압축",
        "하방 돌파"
      ],
      "data_origin": "fallback_synthetic",
      "normalized_quote_volume": 0.0,
      "normalized_open_interest_usd": 0.0,
      "universe_score": 0.0
    }
  ],
  "page_previews": [
    {
      "title": "우선순위",
      "symbol": "SOLUSDT",
      "description": "가장 높은 종합 기회 점수",
      "score": 70.0
    },
    {
      "title": "시그널",
      "symbol": "ETHUSDT",
      "description": "파생 이상치가 가장 큰 심볼",
      "score": 48.2
    },
    {
      "title": "테크니컬 레이팅",
      "symbol": "AVAXUSDT",
      "description": "종합 기술 점수 최상위",
      "score": 86.9
    },
    {
      "title": "추세",
      "symbol": "AVAXUSDT",
      "description": "추세 강도가 가장 강한 심볼",
      "score": 89.6
    },
    {
      "title": "모멘텀",
      "symbol": "AVAXUSDT",
      "description": "모멘텀 강도가 가장 큰 심볼",
      "score": 57.8
    },
    {
      "title": "변동성",
      "symbol": "XRPUSDT",
      "description": "돌파/압축 상태가 가장 뚜렷한 심볼",
      "score": 93.3
    }
  ],
  "strong_recommendations": {
    "5m": {
      "timeframe": "5m",
      "timeframe_label": "5m",
      "long": {
        "timeframe": "5m",
        "timeframe_label": "5m",
        "side": "long",
        "side_label": "롱",
        "symbol": "SOLUSDT",
        "empty": false,
        "opportunity": 75.8,
        "technical_rating": "Strong Buy",
        "trend_bias": "상승 추세",
        "momentum_bias": "과매수",
        "setup_bias": "롱 우위",
        "change_24h": 3.6,
        "last_price": 80.06
      },
      "short": {
        "timeframe": "5m",
        "timeframe_label": "5m",
        "side": "short",
        "side_label": "숏",
        "symbol": "AVAXUSDT",
        "empty": false,
        "opportunity": 69.7,
        "technical_rating": "Strong Sell",
        "trend_bias": "하락 추세",
        "momentum_bias": "과매도",
        "setup_bias": "숏 우위",
        "change_24h": -5.4,
        "last_price": 38.14
      }
    },
    "15m": {
      "timeframe": "15m",
      "timeframe_label": "15m",
      "long": {
        "timeframe": "15m",
        "timeframe_label": "15m",
        "side": "long",
        "side_label": "롱",
        "symbol": "SOLUSDT",
        "empty": false,
        "opportunity": 75.7,
        "technical_rating": "Strong Buy",
        "trend_bias": "상승 추세",
        "momentum_bias": "과매수",
        "setup_bias": "롱 우위",
        "change_24h": 3.6,
        "last_price": 80.06
      },
      "short": {
        "timeframe": "15m",
        "timeframe_label": "15m",
        "side": "short",
        "side_label": "숏",
        "symbol": "XRPUSDT",
        "empty": false,
        "opportunity": 69.1,
        "technical_rating": "Strong Sell",
        "trend_bias": "하락 추세",
        "momentum_bias": "과매도",
        "setup_bias": "숏 우위",
        "change_24h": -4.5,
        "last_price": 0.642
      }
    },
    "1h": {
      "timeframe": "1h",
      "timeframe_label": "1h",
      "long": {
        "timeframe": "1h",
        "timeframe_label": "1h",
        "side": "long",
        "side_label": "롱",
        "symbol": "SOLUSDT",
        "empty": false,
        "opportunity": 70.0,
        "technical_rating": "Buy",
        "trend_bias": "상승 추세",
        "momentum_bias": "과매도",
        "setup_bias": "롱 우위",
        "change_24h": 3.6,
        "last_price": 80.06
      },
      "short": {
        "timeframe": "1h",
        "timeframe_label": "1h",
        "side": "short",
        "side_label": "숏",
        "symbol": "AVAXUSDT",
        "empty": false,
        "opportunity": 69.9,
        "technical_rating": "Strong Sell",
        "trend_bias": "하락 추세",
        "momentum_bias": "과매도",
        "setup_bias": "숏 우위",
        "change_24h": -5.4,
        "last_price": 38.14
      }
    },
    "4h": {
      "timeframe": "4h",
      "timeframe_label": "4h",
      "long": {
        "timeframe": "4h",
        "timeframe_label": "4h",
        "side": "long",
        "side_label": "롱",
        "symbol": "BTCUSDT",
        "empty": false,
        "opportunity": 73.7,
        "technical_rating": "Strong Buy",
        "trend_bias": "상승 추세",
        "momentum_bias": "과매수",
        "setup_bias": "롱 우위",
        "change_24h": 1.8,
        "last_price": 68320.0
      },
      "short": {
        "timeframe": "4h",
        "timeframe_label": "4h",
        "side": "short",
        "side_label": "숏",
        "symbol": "AVAXUSDT",
        "empty": false,
        "opportunity": 70.3,
        "technical_rating": "Strong Sell",
        "trend_bias": "하락 추세",
        "momentum_bias": "과매도",
        "setup_bias": "숏 우위",
        "change_24h": -5.4,
        "last_price": 38.14
      }
    }
  },
  "data_origin": "batch_fallback",
  "fallback_reason": "실시간 Binance 요청 실패 또는 제한 시 표시하는 최근 배치 fallback 데이터입니다.",
  "fallback_generated_at": "2026-04-17T00:00:52+00:00"
}
