{
  "generated_at": "2026-07-21T14:27:04+00:00",
  "scan_id": "scan-top100-15m",
  "market": "binance-usdt-perpetual",
  "universe_key": "top100",
  "universe_label": "Top 100 Symbols",
  "timeframe": "15m",
  "timeframe_label": "15m",
  "result": {
    "pattern": "AB=CD",
    "status": "complete",
    "status_label": "Complete",
    "score": 89.5,
    "score_breakdown": {
      "ratio_fit": 39.3,
      "geometry": 19.5,
      "reaction": 20.0,
      "indicators": 10.7
    },
    "summary": "AB=CD 패턴이 PRZ 구간에 진입했고 Complete 상태로 분류되었습니다.",
    "preview_image": "generated/scanner/scan-top100-15m/pumpusdt-ab-cd-complete.svg",
    "detail_page": "crypto/setups/scan-top100-15m/2026-07-21t05-15-00-00-00-ab-cd-bearish-0-002075/",
    "legacy_detail_page": "patterns/15m/pumpusdt-0d04252389/",
    "detail_data_path": "setups/scan-top100-15m/2026-07-21t05-15-00-00-00-ab-cd-bearish-0-002075.json",
    "side": "bearish",
    "side_label": "Bearish (매도)",
    "prz": {
      "lower": 0.002044,
      "upper": 0.002081,
      "center": 0.002063,
      "distance_pct": 0.604
    },
    "targets": {
      "tp1": 0.002044,
      "tp2": 0.002024
    },
    "stop": {
      "value": 0.002089,
      "label": "1.13 XA"
    },
    "points": {
      "X": {
        "price": 0.002097,
        "timestamp": "2026-07-20T20:00:00+00:00",
        "index": 146
      },
      "A": {
        "price": 0.001989,
        "timestamp": "2026-07-20T22:15:00+00:00",
        "index": 155
      },
      "B": {
        "price": 0.00204,
        "timestamp": "2026-07-21T01:15:00+00:00",
        "index": 167
      },
      "C": {
        "price": 0.001993,
        "timestamp": "2026-07-21T02:00:00+00:00",
        "index": 170
      },
      "D": {
        "price": 0.002075,
        "timestamp": "2026-07-21T05:15:00+00:00",
        "index": 183
      }
    },
    "ratios": {
      "xab": 0.472,
      "abc": 0.922,
      "bcd": 1.745,
      "xad": 0.204
    },
    "indicator_flags": [
      {
        "key": "rsi",
        "label": "RSI",
        "status": "neutral",
        "value": "37.0",
        "note": "과매도/과매수 구간 접근"
      },
      {
        "key": "macd",
        "label": "MACD",
        "status": "pass",
        "value": "-0.0000",
        "note": "히스토그램 반전 확인"
      },
      {
        "key": "bollinger",
        "label": "Bollinger",
        "status": "neutral",
        "value": "0.0019 ~ 0.0020",
        "note": "밴드 극단값 근접"
      },
      {
        "key": "vwap",
        "label": "VWAP",
        "status": "pass",
        "value": "0.0020",
        "note": "VWAP 회복/이탈 흐름"
      },
      {
        "key": "funding",
        "label": "Funding",
        "status": "pass",
        "value": "0.0050%",
        "note": "반대 포지션 과열 여부"
      },
      {
        "key": "open_interest",
        "label": "Open Interest",
        "status": "pass",
        "value": "$54,336,340",
        "note": "체결 관심도 유지"
      },
      {
        "key": "long_short",
        "label": "Long/Short",
        "status": "pass",
        "value": "1.52",
        "note": "군중 포지션 반대편 우위"
      }
    ]
  },
  "analysis": {
    "symbol": "PUMPUSDT",
    "timeframe": "15m",
    "timeframe_label": "15m",
    "last_price": 0.001955,
    "change_24h": 0.56,
    "quote_volume": 136917049.86,
    "funding_rate": 0.005,
    "open_interest_usd": 54336339.88,
    "long_short_ratio": 1.522,
    "liquidation_pressure_usd": 1885.78,
    "scores": {
      "moving_average": -56.0,
      "oscillator": -32.0,
      "technical": -43.7,
      "trend": 54.9,
      "trend_bias": -52.0,
      "momentum": 29.3,
      "momentum_bias": -29.3,
      "volatility": 91.7,
      "derivatives": 23.8,
      "derivatives_bias": -35.0,
      "opportunity": 83.7,
      "setup_bias": -43.7
    },
    "labels": {
      "technical_rating": "Sell",
      "trend_bias": "하락 추세",
      "momentum_bias": "하락 모멘텀",
      "volatility_state": "압축",
      "derivatives_bias": "롱 과밀",
      "setup_bias": "숏 우위"
    },
    "side": "short",
    "side_label": "숏",
    "signals": {
      "squeeze": true,
      "breakout_up": false,
      "breakout_down": false,
      "divergence_candidate": false,
      "supertrend": "bearish",
      "ichimoku_bias": "bearish"
    },
    "indicators": {
      "ema20": 0.001977,
      "ema50": 0.001998,
      "ema200": 0.001927,
      "rsi14": 37.01,
      "stoch_rsi": 55.81,
      "macd_line": -2e-05,
      "macd_signal": -2e-05,
      "macd_histogram": -0.0,
      "bollinger_lower": 0.00193,
      "bollinger_mid": 0.001983,
      "bollinger_upper": 0.002035,
      "bb_width": 5.29,
      "atr14": 1.7e-05,
      "atr_pct": 0.89,
      "adx14": 31.09,
      "plus_di": 17.38,
      "minus_di": 30.86,
      "supertrend_value": 0.002,
      "vwap": 0.001964,
      "close_vs_vwap_pct": -0.47,
      "roc12": -1.91,
      "ichimoku": {
        "tenkan": 0.001958,
        "kijun": 0.001995,
        "span_a": 0.001976,
        "span_b": 0.002003,
        "bias": "bearish"
      }
    },
    "pattern": {
      "pattern": "AB=CD",
      "status": "complete",
      "status_label": "Complete",
      "score": 89.5,
      "score_breakdown": {
        "ratio_fit": 39.3,
        "geometry": 19.5,
        "reaction": 20.0,
        "indicators": 10.7
      },
      "summary": "AB=CD 패턴이 PRZ 구간에 진입했고 Complete 상태로 분류되었습니다.",
      "preview_image": "generated/scanner/scan-top100-15m/pumpusdt-ab-cd-complete.svg",
      "detail_page": "crypto/setups/scan-top100-15m/2026-07-21t05-15-00-00-00-ab-cd-bearish-0-002075/",
      "legacy_detail_page": "patterns/15m/pumpusdt-0d04252389/",
      "detail_data_path": "setups/scan-top100-15m/2026-07-21t05-15-00-00-00-ab-cd-bearish-0-002075.json",
      "side": "bearish",
      "side_label": "Bearish (매도)",
      "prz": {
        "lower": 0.002044,
        "upper": 0.002081,
        "center": 0.002063,
        "distance_pct": 0.604
      },
      "targets": {
        "tp1": 0.002044,
        "tp2": 0.002024
      },
      "stop": {
        "value": 0.002089,
        "label": "1.13 XA"
      },
      "points": {
        "X": {
          "price": 0.002097,
          "timestamp": "2026-07-20T20:00:00+00:00",
          "index": 146
        },
        "A": {
          "price": 0.001989,
          "timestamp": "2026-07-20T22:15:00+00:00",
          "index": 155
        },
        "B": {
          "price": 0.00204,
          "timestamp": "2026-07-21T01:15:00+00:00",
          "index": 167
        },
        "C": {
          "price": 0.001993,
          "timestamp": "2026-07-21T02:00:00+00:00",
          "index": 170
        },
        "D": {
          "price": 0.002075,
          "timestamp": "2026-07-21T05:15:00+00:00",
          "index": 183
        }
      },
      "ratios": {
        "xab": 0.472,
        "abc": 0.922,
        "bcd": 1.745,
        "xad": 0.204
      },
      "indicator_flags": [
        {
          "key": "rsi",
          "label": "RSI",
          "status": "neutral",
          "value": "37.0",
          "note": "과매도/과매수 구간 접근"
        },
        {
          "key": "macd",
          "label": "MACD",
          "status": "pass",
          "value": "-0.0000",
          "note": "히스토그램 반전 확인"
        },
        {
          "key": "bollinger",
          "label": "Bollinger",
          "status": "neutral",
          "value": "0.0019 ~ 0.0020",
          "note": "밴드 극단값 근접"
        },
        {
          "key": "vwap",
          "label": "VWAP",
          "status": "pass",
          "value": "0.0020",
          "note": "VWAP 회복/이탈 흐름"
        },
        {
          "key": "funding",
          "label": "Funding",
          "status": "pass",
          "value": "0.0050%",
          "note": "반대 포지션 과열 여부"
        },
        {
          "key": "open_interest",
          "label": "Open Interest",
          "status": "pass",
          "value": "$54,336,340",
          "note": "체결 관심도 유지"
        },
        {
          "key": "long_short",
          "label": "Long/Short",
          "status": "pass",
          "value": "1.52",
          "note": "군중 포지션 반대편 우위"
        }
      ]
    },
    "flags": [
      "볼린저 압축"
    ],
    "normalized_quote_volume": 1.22,
    "normalized_open_interest_usd": 0.77,
    "universe_score": 1.06
  },
  "related_timeframes": {
    "5m": {
      "technical_rating": "Sell",
      "trend_bias": "하락 추세",
      "momentum_bias": "중립",
      "opportunity": 79.4
    },
    "15m": {
      "technical_rating": "Sell",
      "trend_bias": "하락 추세",
      "momentum_bias": "하락 모멘텀",
      "opportunity": 83.7
    },
    "1h": {
      "technical_rating": "Neutral",
      "trend_bias": "상승 추세",
      "momentum_bias": "과매도",
      "opportunity": 71.3
    },
    "4h": {
      "technical_rating": "Strong Buy",
      "trend_bias": "상승 추세",
      "momentum_bias": "상승 모멘텀",
      "opportunity": 78.1
    }
  }
}
