{
  "generated_at": "2026-04-06T03:54:04+00:00",
  "scan_id": "scan-top100-4h",
  "market": "binance-usdt-perpetual",
  "universe_key": "top100",
  "universe_label": "상위 100개 종목",
  "timeframe": "4h",
  "timeframe_label": "4시간 (4h)",
  "result": {
    "pattern": "AB=CD",
    "status": "complete",
    "status_label": "일반 완성",
    "score": 81.2,
    "score_breakdown": {
      "ratio_fit": 39.1,
      "geometry": 11.4,
      "reaction": 20.0,
      "indicators": 10.7
    },
    "summary": "AB=CD 패턴이 PRZ 구간에 진입했고 일반 완성 상태로 분류되었습니다.",
    "preview_image": "generated/scanner/scan-top100-4h/maskusdt-ab-cd-complete.svg",
    "detail_page": "crypto/setups/scan-top100-4h/2026-04-05t12-00-00-00-00-ab-cd-bearish-0-5177/",
    "legacy_detail_page": "patterns/4h/maskusdt-e99276a89f/",
    "detail_data_path": "setups/scan-top100-4h/2026-04-05t12-00-00-00-00-ab-cd-bearish-0-5177.json",
    "side": "bearish",
    "side_label": "Bearish (매도)",
    "prz": {
      "lower": 0.50607,
      "upper": 0.5359,
      "center": 0.52099,
      "distance_pct": 0.631
    },
    "targets": {
      "tp1": 0.49379,
      "tp2": 0.47901
    },
    "stop": {
      "value": 0.52055,
      "label": "1.13 XA"
    },
    "points": {
      "X": {
        "price": 0.4234,
        "timestamp": "2026-04-01T16:00:00+00:00",
        "index": 193
      },
      "A": {
        "price": 0.4015,
        "timestamp": "2026-04-02T00:00:00+00:00",
        "index": 195
      },
      "B": {
        "price": 0.4823,
        "timestamp": "2026-04-04T12:00:00+00:00",
        "index": 210
      },
      "C": {
        "price": 0.4551,
        "timestamp": "2026-04-05T04:00:00+00:00",
        "index": 214
      },
      "D": {
        "price": 0.5177,
        "timestamp": "2026-04-05T12:00:00+00:00",
        "index": 216
      }
    },
    "ratios": {
      "xab": 3.689,
      "abc": 0.337,
      "bcd": 2.301,
      "xad": 4.306
    },
    "indicator_flags": [
      {
        "key": "rsi",
        "label": "RSI",
        "status": "pass",
        "value": "52.5",
        "note": "과매도/과매수 구간 접근"
      },
      {
        "key": "macd",
        "label": "MACD",
        "status": "pass",
        "value": "-0.0012",
        "note": "히스토그램 반전 확인"
      },
      {
        "key": "bollinger",
        "label": "Bollinger",
        "status": "neutral",
        "value": "0.4316 ~ 0.4960",
        "note": "밴드 극단값 근접"
      },
      {
        "key": "vwap",
        "label": "VWAP",
        "status": "neutral",
        "value": "0.4508",
        "note": "VWAP 회복/이탈 흐름"
      },
      {
        "key": "funding",
        "label": "Funding",
        "status": "pass",
        "value": "0.0050%",
        "note": "반대 포지션 과열 여부"
      },
      {
        "key": "open_interest",
        "label": "Open Interest",
        "status": "pass",
        "value": "$2,702,667",
        "note": "체결 관심도 유지"
      },
      {
        "key": "long_short",
        "label": "Long/Short",
        "status": "pass",
        "value": "1.37",
        "note": "군중 포지션 반대편 우위"
      }
    ]
  },
  "analysis": {
    "symbol": "MASKUSDT",
    "timeframe": "4h",
    "timeframe_label": "4시간 (4h)",
    "last_price": 0.4624,
    "change_24h": -0.54,
    "quote_volume": 24886882.49,
    "funding_rate": 0.005,
    "open_interest_usd": 2702666.82,
    "long_short_ratio": 1.373,
    "liquidation_pressure_usd": 489.22,
    "scores": {
      "moving_average": 50.0,
      "oscillator": -33.3,
      "technical": 24.0,
      "trend": 53.4,
      "trend_bias": 40.6,
      "momentum": 22.9,
      "momentum_bias": -22.9,
      "volatility": 72,
      "derivatives": 17.2,
      "derivatives_bias": -35.0,
      "opportunity": 69.8
    },
    "labels": {
      "technical_rating": "Buy",
      "trend_bias": "상승 추세",
      "momentum_bias": "과매도",
      "volatility_state": "확장",
      "derivatives_bias": "롱 과밀"
    },
    "signals": {
      "squeeze": false,
      "breakout_up": false,
      "breakout_down": false,
      "divergence_candidate": false,
      "supertrend": "bullish",
      "ichimoku_bias": "neutral"
    },
    "indicators": {
      "ema20": 0.46094,
      "ema50": 0.44404,
      "ema200": 0.44421,
      "rsi14": 52.5,
      "stoch_rsi": 12.81,
      "macd_line": 0.01273,
      "macd_signal": 0.01393,
      "macd_histogram": -0.0012,
      "bollinger_lower": 0.43164,
      "bollinger_mid": 0.46383,
      "bollinger_upper": 0.49603,
      "bb_width": 13.88,
      "atr14": 0.024929,
      "atr_pct": 5.39,
      "adx14": 43.08,
      "plus_di": 22.7,
      "minus_di": 23.66,
      "supertrend_value": 0.4166,
      "vwap": 0.45083,
      "close_vs_vwap_pct": 2.57,
      "roc12": -1.05,
      "ichimoku": {
        "tenkan": 0.4709,
        "kijun": 0.4596,
        "span_a": 0.46525,
        "span_b": 0.45215,
        "bias": "neutral"
      }
    },
    "pattern": {
      "pattern": "AB=CD",
      "status": "complete",
      "status_label": "일반 완성",
      "score": 81.2,
      "score_breakdown": {
        "ratio_fit": 39.1,
        "geometry": 11.4,
        "reaction": 20.0,
        "indicators": 10.7
      },
      "summary": "AB=CD 패턴이 PRZ 구간에 진입했고 일반 완성 상태로 분류되었습니다.",
      "preview_image": "generated/scanner/scan-top100-4h/maskusdt-ab-cd-complete.svg",
      "detail_page": "crypto/setups/scan-top100-4h/2026-04-05t12-00-00-00-00-ab-cd-bearish-0-5177/",
      "legacy_detail_page": "patterns/4h/maskusdt-e99276a89f/",
      "detail_data_path": "setups/scan-top100-4h/2026-04-05t12-00-00-00-00-ab-cd-bearish-0-5177.json",
      "side": "bearish",
      "side_label": "Bearish (매도)",
      "prz": {
        "lower": 0.50607,
        "upper": 0.5359,
        "center": 0.52099,
        "distance_pct": 0.631
      },
      "targets": {
        "tp1": 0.49379,
        "tp2": 0.47901
      },
      "stop": {
        "value": 0.52055,
        "label": "1.13 XA"
      },
      "points": {
        "X": {
          "price": 0.4234,
          "timestamp": "2026-04-01T16:00:00+00:00",
          "index": 193
        },
        "A": {
          "price": 0.4015,
          "timestamp": "2026-04-02T00:00:00+00:00",
          "index": 195
        },
        "B": {
          "price": 0.4823,
          "timestamp": "2026-04-04T12:00:00+00:00",
          "index": 210
        },
        "C": {
          "price": 0.4551,
          "timestamp": "2026-04-05T04:00:00+00:00",
          "index": 214
        },
        "D": {
          "price": 0.5177,
          "timestamp": "2026-04-05T12:00:00+00:00",
          "index": 216
        }
      },
      "ratios": {
        "xab": 3.689,
        "abc": 0.337,
        "bcd": 2.301,
        "xad": 4.306
      },
      "indicator_flags": [
        {
          "key": "rsi",
          "label": "RSI",
          "status": "pass",
          "value": "52.5",
          "note": "과매도/과매수 구간 접근"
        },
        {
          "key": "macd",
          "label": "MACD",
          "status": "pass",
          "value": "-0.0012",
          "note": "히스토그램 반전 확인"
        },
        {
          "key": "bollinger",
          "label": "Bollinger",
          "status": "neutral",
          "value": "0.4316 ~ 0.4960",
          "note": "밴드 극단값 근접"
        },
        {
          "key": "vwap",
          "label": "VWAP",
          "status": "neutral",
          "value": "0.4508",
          "note": "VWAP 회복/이탈 흐름"
        },
        {
          "key": "funding",
          "label": "Funding",
          "status": "pass",
          "value": "0.0050%",
          "note": "반대 포지션 과열 여부"
        },
        {
          "key": "open_interest",
          "label": "Open Interest",
          "status": "pass",
          "value": "$2,702,667",
          "note": "체결 관심도 유지"
        },
        {
          "key": "long_short",
          "label": "Long/Short",
          "status": "pass",
          "value": "1.37",
          "note": "군중 포지션 반대편 우위"
        }
      ]
    },
    "flags": []
  },
  "related_timeframes": {
    "5m": {
      "technical_rating": "Buy",
      "trend_bias": "상승 추세",
      "momentum_bias": "과매도",
      "opportunity": 75.5
    },
    "15m": {
      "technical_rating": "Neutral",
      "trend_bias": "혼조",
      "momentum_bias": "상승 모멘텀",
      "opportunity": 75.3
    },
    "1h": {
      "technical_rating": "Sell",
      "trend_bias": "하락 추세",
      "momentum_bias": "하락 모멘텀",
      "opportunity": 76.4
    },
    "4h": {
      "technical_rating": "Buy",
      "trend_bias": "상승 추세",
      "momentum_bias": "과매도",
      "opportunity": 69.8
    }
  }
}
